{"COMP1521": "Computer Systems Fundamentals", "COMP3331": "Computer Networks and Applications", "COMP2521": "Data Structures and Algorithms", "COMP1511": "Introduction to Programming", "COMP9321": "Data Services Engineering", "COMP9311": "Database Systems", "COMP9444": "Neural Networks and Deep Learning", "COMP3311": "Database Systems", "COMP1531": "Software Engineering Fundamentals", "COMP2511": "Object-Oriented Design & Programming", "COMP9020": "Foundations of Computer Science", "COMP9024": "Data Structures and Algorithms", "COMP9315": "DBMS Implementation", "COMP9313": "Big Data Management"}